# question

## 第1题
**题目：** 尽可能详细地描述如下代码的全过程（从编写到运行）。
```java
public class Person {
    private String name;
    private static String classInfo;
    public Person(String name) {this.name = name;}
    static {
        classInfo = "三班";
    }
    {
        System.out.println("动态块被执行...");
    }
    public static void main(String[] args) {
        Person p = new Person("赵四");
        p.setName("刘能");
        sayHello(p.getName());
    }
    static void sayHello(String name){
        System.out.println("hi I am " + name);
    }
    String getName() {
        return name;
    }
    void setName(String name) {
        this.name = name;
    }
}
```

## 第2题
**题目：** 
 1. 将 `public int method();` 中的字节码进行解析。
 - `public int method();`：
    - `descriptor: ()I`：
    - `flags: ACC_PUBLIC`：
    - `stack=4`：
    - `locals=1`：
    - `args_size=1`：
- `0: aload_0`：
- `1: dup`：
- `2: getfield #2 //Field num:I`：
- `5: dup_x1`：
- `6: iconst_1`：
- `7: iadd`：
- `8: putfield #2 //Field num:I`：
- `11: ireturn`：
- `LineNumberTable:`：
    - `line 10: 0`：
- `LocalVariableTable:`：
    - `Start=0`：
    - `Length=12`：
    - `Slot=0`：
    - `Name=this`：
    - `Signature=.../ByteCodeDemo;`：

# answer

## 第1题
**答案：** 整体分三部分，编写，编译和运行。
1. 编写代码：
    - 在计算机物理硬盘上编写 `Person.java` 文件。
2. 编译代码：
    - 执行命令：`javac Person.java` 
    - 检查java文件的内容是否正确（词法和语法）。
    - 得到 `Person.class` 文件，它也在计算机物理硬盘上。
3. 运行代码，执行运行命令：`java Person`。
4. JVM启动：`Connected to the target VM...`
5. JVM中的 `Bootstrap ClassLoader` 启动。
    - 按需加载 `%JAVA_HOME%\jre\lib` 下的某些的class文件（jar包）。
    - 加载另外两个类加载器。
6. `ExtClassLoader` 去按需加载 `ext` 下的某些class文件（jar包）。
7. `AppClassLoader` 去加载 `classpath` 路径下的 `Person.class`（因为它有main方法）。
    - 检验，准备和解析的工作会在整个加载的过程中交叉执行。
    - `AppClassLoader` 在方法区中创建一个对应 `Person.class` 文件的instanceKlass区域。
    - `AppClassLoader` 开始逐行加载 `Person.class` 中的内容到instanceKlass区域中。
    - `AppClassLoader` 将静态属性 `classInfo`，加载到instanceKlass区域的静态区，并分配初始值为null。
    - `AppClassLoader` 将静态方法 `main()`，加载到instanceKlass区域的静态区。
    - `AppClassLoader` 将静态方法 `sayHello()`，加载到instanceKlass区域的静态区。 
    - `AppClassLoader` 将静态块，加载到instanceKlass区域的静态区。
    - `AppClassLoader` 将动态块，加载到instanceKlass区域的非静态区。
    - `AppClassLoader` 将构造方法 `Person(){}`，加载到instanceKlass区域的非静态区。
    - `AppClassLoader` 将非静态方法 `getName()`，加载到instanceKlass区域的非静态区。
    - `AppClassLoader` 将非静态方法 `setName()`，加载到instanceKlass区域的非静态区。
    - 在堆内存中创建一个对应instanceKlass区域的java.lang.Class对象，模拟内存地址为 `0xAAAA`。
    - 非静态属性 `name`，`AppClassLoader` 会忽略它，非静态属性不进行加载。
8. 进行初始化工作
    - 为静态属性 `classInfo` 赋真正的值。
    - 执行执行静态块，将 `classInfo` 赋值为 "三班"。
9. 执行方法入口main，将其压入栈顶。
10. 执行代码：`Person p = new Person("赵四");`
    - 在堆内存中开辟空间，分配内存地址，模拟为 `0x9527`。
    - 设置实例的对象头：类型指针指向 `0xAAAA`，记录HashCode，分代年龄和锁状态等信息。
    - 设置实例数据区内容：建立非静态属性 `name`，并赋初始值为null。
    - 设置实例的补齐区：如果需要补齐则补齐，不需要则忽略。
    - 执行动态块：输出 "动态块被执行..."。
    - 执行构造函数，将属性 `name` 的值赋值为 "赵四"。
    - 在main方法的方法栈帧中创建一个局部变量 `p`。
    - 将内存地址 `0x9527` 分配给栈中的变量 `p`。
11. 执行代码：`p.setName("刘能")`
    - 在栈内存中开辟 `setName()` 的方法栈帧，其中包含了一个 `this` 和局部变量 `name`。
    - 将 `p` 的值 `0x9527` 赋值给 `this`。
    - 将局部变量 `name` 的值 "刘能" 赋值给 `this.name`。
    - `setName()` 出栈。
12. 执行代码：`p.getName()`
    - 在栈内存中开辟 `getName()` 的方法栈帧，其中包含了一个 `this`。
    - 将 `p` 的值 `0x9527` 赋值给 `this`。
    - 返回 `this.name` 的值，递交给 `sayHello()` 作为方法参数。
    - `getName()` 出栈。
13. 执行代码：`sayHello()`
    - 在栈内存中开辟 `sayHello()` 的方法栈帧，其中包含一个类型指针地址 `0xAAAA` 和局部变量 `name`。
    - 执行输出 "hi I am 刘能"
    - `sayHello()` 出栈。
14. main方法出栈，程序结束：`Disconnected from the target VM`
    

## 第2题
**答案：** 
- `public int method();`
    - `descriptor: ()I`：方法无参，返回值类型为int
    - `flags: ACC_PUBLIC`：方法被public修饰
    - `stack=4`：方法最大操作数栈深为4
    - `locals=1`：方法局部变量表大小为1Slot
    - `args_size=1`：方法参数个数为1，包括隐藏参数this
- `0: aload_0`：将局部变量表中的第1个引用数据类型的值压入栈顶
    - 此时栈顶：`this`：this中存放的是当前实例的内存地址
- `1: dup`：复制栈顶数值并将复制值压入栈顶
    - 此时栈顶：`this` - `this`
- `2: getfield #2 //Field num:I`：获取成员属性（引用常量池中第二个常量），并将其之压入栈顶，获取this.num需要通过this定位，所以会消耗一个this
    - 此时栈顶：`num(0)` - `this`
- `5: dup_x1`：复制两份栈顶数值并将两个复制数值依次压入栈顶，复制this.num需要通过this定位，消耗了一个this
    - 此时栈顶：`num(0)` - `num(0)` - `num(0)`
- `6: iconst_1`：将int型字面量 `1` 压入栈顶
    - 此时栈顶：`1` - `num(0)` - `num(0)` - `num(0)`
- `7: iadd`：将栈顶两值相加并将结果压入栈顶，加法过程需要将栈顶两个值弹出进行操作，弹出的两个值会全被消耗掉
    - 此时栈顶：`1(1+0)` - `num(0)` - `num(0)`
- `8: putfield #2 //Field num:I`：为成员属性（引用常量池中第二个常量）赋值为当前栈顶的值，赋值过程需要将栈顶两个值弹出进行操作，两个值全被消耗掉
    - 此时栈顶：`num(1)`
- `11: ireturn`：返回int类型值，弹出栈中最后剩下的 `num(1)` 的值
    - 此时栈顶：null
- `LineNumberTable:`：行号表
    - `line 10: 0`：源码中第10行对应字节码中的第0条指令
- `LocalVariableTable:`：局部变量表
    - `Start=0`：该局部变量从字节码的第1行开始可见
    - `Length=12`：该局部变量在12行字节码指令之内可见
    - `Slot=0`：该局部变量存储在局部变量表的0号位置
    - `Name=this`：该局部变量的名称为this
    - `Signature=.../ByteCodeDemo;`：该局部变量的类型为ByteCodeDemo